vehicle_tools/__init__.py
vehicle_tools/__main__.py
vehicle_tools-0.1.0.dist-info/AUTHORS
vehicle_tools-0.1.0.dist-info/LICENSE
vehicle_tools-0.1.0.dist-info/METADATA
vehicle_tools-0.1.0.dist-info/WHEEL
vehicle_tools-0.1.0.dist-info/entry_points.txt
vehicle_tools-0.1.0.dist-info/pbr.json
vehicle_tools-0.1.0.dist-info/top_level.txt
vehicle_tools-0.1.0.dist-info/RECORD
