Metadata-Version: 2.1
Name: vehicle-tools
Version: 0.1.0
Summary: UNKNOWN
Home-page: UNKNOWN
Author: UNKNOWN
Author-email: UNKNOWN
License: UNKNOWN
Platform: UNKNOWN
Requires-Dist: pendulum (==2.0.5)
Requires-Dist: python-dateutil (==2.8.1)
Requires-Dist: pytzdata (==2019.3)
Requires-Dist: six (==1.14.0)
